drive2x_sca_interfaces/__init__.py
drive2x_sca_interfaces-0.1.3.dist-info/licenses/LICENSE
drive2x_sca_interfaces-0.1.3.dist-info/METADATA
drive2x_sca_interfaces-0.1.3.dist-info/WHEEL
drive2x_sca_interfaces-0.1.3.dist-info/top_level.txt
drive2x_sca_interfaces-0.1.3.dist-info/RECORD
