Metadata-Version: 2.4
Name: drive2x_sca_interfaces
Version: 0.1.3
Summary: Definitions and validators for DriVe2X SCA integration."
Author-email: Aleksei Romanenko <aleksei.romanenko@lut.fi>
License-Expression: LGPL-2.1-or-later
Project-URL: Homepage, https://github.com/Kreastr/drive2x-sca-interfaces
Project-URL: Issues, https://github.com/Kreastr/drive2x-sca-interfaces/issues
Keywords: D2X,DriVe2X,SCA,Smart,Charging,Algorithm
Classifier: Programming Language :: Python :: 3
Classifier: Operating System :: OS Independent
Requires-Python: >=3.9
License-File: LICENSE
Requires-Dist: pydantic
Dynamic: license-file
